LICENSE
MANIFEST.in
README.md
requirements.txt
setup.py
datasetstation/__init__.py
datasetstation/api.py
datasetstation/backend.py
datasetstation/config.py
datasetstation/error.py
datasetstation/message.py
datasetstation/repo.py
datasetstation/type.py
datasetstation.egg-info/PKG-INFO
datasetstation.egg-info/SOURCES.txt
datasetstation.egg-info/dependency_links.txt
datasetstation.egg-info/entry_points.txt
datasetstation.egg-info/requires.txt
datasetstation.egg-info/top_level.txt
datasetstation/command/__init__.py
datasetstation/command/main.py
datasetstation/command/sync_datasets.py
datasetstation/eda/__init__.py
datasetstation/eda/text.py
datasetstation/eda/video.py
datasetstation/preprocess/__init__.py
datasetstation/preprocess/text/__init__.py
datasetstation/preprocess/text/hanzi.py
datasetstation/preprocess/text/rule_pattern.py
datasetstation/preprocess/text/cleaner/__init__.py
datasetstation/preprocess/text/cleaner/emoji.py
datasetstation/preprocess/text/cleaner/extractor.py
datasetstation/preprocess/text/tokenizer/__init__.py
datasetstation/preprocess/text/tokenizer/chinese.py
datasetstation/preprocess/text/tokenizer/pretokenizer.py
datasetstation/util/__init__.py
datasetstation/util/configuration.py
datasetstation/util/log.py
datasetstation/util/option.py
datasetstation/util/process.py
datasetstation/util/python.py
datasetstation/util/regex.py
datasetstation/util/s3.py
datasetstation/util/strings.py
datasetstation/util/thread.py
datasetstation/util/tool.py
datasetstation/util/track.py